date/__init__.py
opendate-0.1.39.dist-info/METADATA
opendate-0.1.39.dist-info/WHEEL
opendate-0.1.39.dist-info/licenses/LICENSE
opendate/__init__.py
opendate/_opendate.cpython-39-x86_64-linux-gnu.so
opendate/calendars.py
opendate/constants.py
opendate/date_.py
opendate/datetime_.py
opendate/decorators.py
opendate/extras.py
opendate/helpers.py
opendate/interval.py
opendate/metaclass.py
opendate/mixins/__init__.py
opendate/mixins/business.py
opendate/mixins/extras_.py
opendate/time_.py
opendate-0.1.39.dist-info/RECORD
