Metadata-Version: 2.4
Name: opendate
Version: 0.1.39
Classifier: License :: OSI Approved :: MIT License
Classifier: Programming Language :: Python :: 3
Classifier: Programming Language :: Python :: 3.9
Classifier: Programming Language :: Python :: 3.10
Classifier: Programming Language :: Python :: 3.11
Classifier: Programming Language :: Python :: 3.12
Requires-Dist: pandas-market-calendars
Requires-Dist: pendulum
Requires-Dist: wrapt
Requires-Dist: typing-extensions
Requires-Dist: asserts ; extra == 'test'
Requires-Dist: pdbpp ; extra == 'test'
Requires-Dist: pytest ; extra == 'test'
Requires-Dist: bump2version ; extra == 'test'
Provides-Extra: test
License-File: LICENSE
Summary: Python business datetimes
Author-email: bissli <bissli.xyz@protonmail.com>
Requires-Python: >=3.9
Project-URL: Repository, https://github.com/bissli/opendate
